README.rst
setup.py
django_multiforeignkey.egg-info/PKG-INFO
django_multiforeignkey.egg-info/SOURCES.txt
django_multiforeignkey.egg-info/dependency_links.txt
django_multiforeignkey.egg-info/requires.txt
django_multiforeignkey.egg-info/top_level.txt
multiforeignkey/__init__.py
multiforeignkey/models.py