Metadata-Version: 1.0
Name: django-multiforeignkey
Version: 0.0.2
Summary: Django ForeignKey that links to one of several specified models
Home-page: https://github.com/IlyaSemenov/django-multiforeignkey
Author: Ilya Semenov
Author-email: ilya@semenov.co
License: BSD
Platform: UNKNOWN
